wall_of_text_api_wrapper/__init__.py
wall_of_text_api_wrapper/api_versions/__init__.py
wall_of_text_api_wrapper/api_versions/v1/__init__.py
wall_of_text_api_wrapper/api_versions/v1/dataclasses.py
wall_of_text_api_wrapper/api_versions/v1/wrapper.py
wall_of_text_api_wrapper-1.0.1.dist-info/LICENSE.txt
wall_of_text_api_wrapper-1.0.1.dist-info/METADATA
wall_of_text_api_wrapper-1.0.1.dist-info/WHEEL
wall_of_text_api_wrapper-1.0.1.dist-info/top_level.txt
wall_of_text_api_wrapper-1.0.1.dist-info/RECORD
