Metadata-Version: 2.2
Name: wall_of_text_api_wrapper
Version: 1.0.1
Summary: Python wrapper for the Wall Of Text API
Author-email: Pashok11 <pasha.m220@gmail.com>
License: MIT License
Project-URL: Homepage, https://github.com/Pashok111/Wall-Of-Text-API-Wrapper
Project-URL: Repository, https://github.com/Pashok111/Wall-Of-Text-API-Wrapper.git
Project-URL: Issues, https://github.com/Pashok111/Wall-Of-Text-API-Wrapper/issues
Keywords: wall of text,wot,api,wrapper,pashok11
Classifier: Programming Language :: Python :: 3
Classifier: Operating System :: OS Independent
Requires-Python: >=3.8
License-File: LICENSE.txt
Requires-Dist: requests
